windbreads/__init__.py
windbreads/auto.py
windbreads/common_i18n.py
windbreads/security.py
windbreads/utils.py
windbreads-2021.8.31.dist-info/LICENSE
windbreads-2021.8.31.dist-info/METADATA
windbreads-2021.8.31.dist-info/WHEEL
windbreads-2021.8.31.dist-info/top_level.txt
windbreads-2021.8.31.dist-info/RECORD
